<?xml version="1.0" encoding="utf-8"?>
<Patch>

    <Operation Class="VFECore.PatchOperationToggableSequence">
        <enabled>True</enabled>
        <mods>
            <li>Medieval Overhaul</li>
            <li>More Linkables</li>
        </mods>
        <label>More Linkables + Medieval Overhaul integration:</label>
        <operations>
            <li Class="PatchOperationAdd">
                <success>Always</success>
                <xpath>/Defs/ThingDef[defName="DankPyon_RusticCookingTable" or
                                      defName="DankPyon_ButchersBlock" or
                                      defName="DankPyon_StoneOven" or
                                      defName="DankPyon_Grill" or
                                      defName="DankPyon_MillStone"
                ]/comps/li[@Class="CompProperties_AffectedByFacilities"]/linkableFacilities</xpath>
                <value>
                    <li>KitchenCupboard</li>
                </value>
            </li>
        </operations>
    </Operation>
</Patch>
